vector_etl/__init__.py
vector_etl/flow.py
vector_etl/main.py
vector_etl/orchestrator.py
vector_etl/embedding_mods/__init__.py
vector_etl/embedding_mods/azure_openai.py
vector_etl/embedding_mods/base.py
vector_etl/embedding_mods/cohere.py
vector_etl/embedding_mods/google_gemini.py
vector_etl/embedding_mods/huggingface.py
vector_etl/embedding_mods/openai.py
vector_etl/source_mods/__init__.py
vector_etl/source_mods/base.py
vector_etl/source_mods/box_loader.py
vector_etl/source_mods/database_loader.py
vector_etl/source_mods/dropbox_loader.py
vector_etl/source_mods/file_loader.py
vector_etl/source_mods/google_cloud_storage.py
vector_etl/source_mods/google_drive.py
vector_etl/source_mods/local_file.py
vector_etl/source_mods/s3_loader.py
vector_etl/source_mods/stripe_loader.py
vector_etl/source_mods/zendesk_loader.py
vector_etl/source_mods/backup/__init__.py
vector_etl/source_mods/backup/dropbox_loader_bkp.py
vector_etl/source_mods/backup/google_cloud_storage_bkp.py
vector_etl/source_mods/backup/local_file_bkp.py
vector_etl/source_mods/backup/old_init.py
vector_etl/source_mods/backup/s3_loader_bkp.py
vector_etl/target_mods/__init__.py
vector_etl/target_mods/base.py
vector_etl/target_mods/lancedb.py
vector_etl/target_mods/milvus.py
vector_etl/target_mods/mongodb.py
vector_etl/target_mods/neo4j.py
vector_etl/target_mods/pinecone.py
vector_etl/target_mods/qdrant.py
vector_etl/target_mods/singlestore.py
vector_etl/target_mods/supabase.py
vector_etl/target_mods/tembo.py
vector_etl/target_mods/weaviate.py
vector_etl-0.1.7.1.dist-info/LICENSE.txt
vector_etl-0.1.7.1.dist-info/METADATA
vector_etl-0.1.7.1.dist-info/WHEEL
vector_etl-0.1.7.1.dist-info/entry_points.txt
vector_etl-0.1.7.1.dist-info/top_level.txt
vector_etl-0.1.7.1.dist-info/RECORD
