Metadata-Version: 2.1
Name: vector-etl
Version: 0.1.7.1
Summary: Lightweight ETL Framework for Vector Databases
Home-page: https://github.com/ContextData/vector_etl
Author: Jide Ogunjobi
Author-email: Jide Ogunjobi <jide@contextdata.ai>
License: BSD-3-Clause
Keywords: vector database,etl
Classifier: Programming Language :: Python :: 3
Requires-Python: >=3.7
License-File: LICENSE.txt
Requires-Dist: boto3
Requires-Dist: botocore
Requires-Dist: cohere
Requires-Dist: cffi
Requires-Dist: openai
Requires-Dist: psycopg2-binary
Requires-Dist: pinecone-client
Requires-Dist: requests
Requires-Dist: tiktoken
Requires-Dist: python-dotenv
Requires-Dist: pydantic
Requires-Dist: mysql-connector-python
Requires-Dist: pymysql
Requires-Dist: pandas
Requires-Dist: qdrant-client
Requires-Dist: singlestoredb
Requires-Dist: weaviate-client
Requires-Dist: azure-storage-blob
Requires-Dist: google-cloud-storage
Requires-Dist: snowflake-connector-python
Requires-Dist: stripe
Requires-Dist: vecs
Requires-Dist: simple-salesforce
Requires-Dist: google-generativeai
Requires-Dist: anthropic
Requires-Dist: pympler
Requires-Dist: unstructured[all-docs]
Requires-Dist: dropbox
Requires-Dist: zenpy
Requires-Dist: lancedb
Requires-Dist: pyyaml
Requires-Dist: google-auth
Requires-Dist: google-auth-oauthlib
Requires-Dist: google-auth-httplib2
Requires-Dist: google-api-python-client
Requires-Dist: unstructured-client
Requires-Dist: box-sdk-gen
Requires-Dist: pymongo
Requires-Dist: neo4j
Requires-Dist: python-magic
Requires-Dist: pytest
Requires-Dist: nltk
Requires-Dist: pymilvus
